divspl/__init__.py
divspl/boxes.py
divspl/divspl.py
divspl/lexer.py
divspl/main.py
divspl/parser.py
divspl/target.py
divspl-0.0.4.dist-info/DESCRIPTION.rst
divspl-0.0.4.dist-info/METADATA
divspl-0.0.4.dist-info/RECORD
divspl-0.0.4.dist-info/WHEEL
divspl-0.0.4.dist-info/entry_points.txt
divspl-0.0.4.dist-info/metadata.json
divspl-0.0.4.dist-info/top_level.txt
