Metadata-Version: 2.0
Name: divspl
Version: 0.0.4
Summary: Dustin Ingram's Very Special Programming Language.
Home-page: https://github.com/di/divspl
Author: Dustin Ingram
Author-email: github@dustingram.com
License: MIT
Keywords: fizz buzz rply
Platform: UNKNOWN
Classifier: Intended Audience :: Developers
Requires-Dist: rply
